{
  "title": "The Recycled Citizen",
  "description": "Sarah Kelling and her husband, Max Bittersohn, have joined the rest of the Kelling clan to plan a black-tie charity auction with the proceeds going to the Senior Citizens' Recycling Center. But soon one of the Center's members is killed, and the Kelling clan enlists Sarah and Max to solve the mystery and save the Kelling name.",
  "genres": [
    "Mystery",
    "Fiction",
    "Cozy Mystery",
    "Cozy",
    "Humor",
    "Audiobook",
    "Mystery Thriller"
  ],
  "author": "Charlotte MacLeod",
  "average_rating": "4.01",
  "url": "https://www.goodreads.com/book/show/1870651.The_Recycled_Citizen"
}