{
  "title": "Influential Magic",
  "description": "It’s tough being a faery in New Orleans, a city fraught with vampires… especially when their very existence drains your life-force.Willow Rhoswen, owner of The Fated Cupcake and part-time vampire hunter for the Void is having a rough week. Four years after her twin brother’s mysterious death, Willow’s life is threatened and the director saddles her with a new partner—her ex-boyfriend, David. To her horror, he’s turned vamp, which causes her physical pain whenever she touches him… and any other specimen of the undead.In order to save Willow’s life, David agrees to turn double agent against the most powerful vampire organization in New Orleans. Or so he says. And she’s convinced they know something about her brother’s death. Unsure where David’s loyalties lie, she turns to Talisen, her childhood crush, to help her solve the mystery.Caught between two gorgeous men and a director who’ll stop at nothing to control Willow’s gifts, she’ll have to follow her instincts and learn who to trust. Otherwise, she risks losing more than just her life.",
  "genres": [
    "Fantasy",
    "Paranormal",
    "Vampires",
    "Fae",
    "Romance",
    "Urban Fantasy",
    "Paranormal Romance"
  ],
  "author": "Deanna Chase",
  "average_rating": "3.84",
  "url": "https://www.goodreads.com/book/show/18857205-influential-magic"
}