{
  "title": "Geschöpf der Finsternis",
  "description": "Mit einem Dolch in der Hand durchstreift Elise Chase die Straßen von Boston, um Rache an den Vampiren zu nehmen. Ihre übersinnlichen Kräfte helfen ihr, die Beute aufspüren, doch diese Gabe ist nicht ungefährlich. Als Lehrmeister hat sie sich ausgerechnet Tegan ausgesucht, den tödlichsten aller Vampirkrieger …Dritter Roman der begeistert aufgenommenen Fantasy-Romance-Serie.",
  "genres": [
    "Paranormal Romance",
    "Paranormal",
    "Vampires",
    "Romance",
    "Fantasy",
    "Urban Fantasy",
    "Adult"
  ],
  "author": "Lara Adrian",
  "average_rating": "4.23",
  "url": "https://www.goodreads.com/book/show/19241254-gesch-pf-der-finsternis"
}