{
  "title": "Fear the Light",
  "description": "WHO MURDERED DRACULA?Many had tried to kill the Count over the centuries. All had failed. Until now...Eight vampires gather at their maker's castle to solve the mystery of who killed Dracula. But as the sun rises outside the chateau, a voice cries out and another vampire is slain. Trapped inside their master's lair, the sun burning bright outside, Dracula's children realize that they have met their match - a formidable killer who plans on picking them off one by one! As the daylight reigns and their numbers dwindle, a dark suspicion grows - could the killer be hiding in plain sight?",
  "genres": [
    "Horror",
    "Vampires",
    "Paranormal",
    "Urban Fantasy",
    "Mystery Thriller",
    "Thriller",
    "Fiction"
  ],
  "author": "William Massa",
  "average_rating": "3.86",
  "url": "https://www.goodreads.com/book/show/23670984-fear-the-light"
}