{
  "title": "Classic Crews: A Harry Crews Reader",
  "description": "From Simon & Schuster, Classic Crews is a collection of works from the master Harry Crews, including his memoir and short stories.Collected here is the best of Harry his astoundingly beautiful memoir A The Biography of a Place ; two if his most memorable novels, Car and The Gypsy's Curse ; and three masterly essays, \"Climbing the Tower,\" \"The Car,\" and \"Fathers, Sons and Blood,\" as well as a new introduction to these works by Crews himself.",
  "genres": [
    "Fiction",
    "Southern",
    "Short Stories",
    "Essays",
    "Literature",
    "Southern Gothic",
    "20th Century"
  ],
  "author": "Harry Crews",
  "average_rating": "4.36",
  "url": "https://www.goodreads.com/book/show/24844.Classic_Crews"
}