{
  "title": "Once Upon Now",
  "description": "An exclusive collection of new modern tales with a fantastical twist, from some of the most beloved writers on Wattpad.Discover this anthology of everyday stories influenced by fairytales and mythology—from ten Wattpad authors, all voted by the site’s users, featuring your favorite celebrities, all with a touch of fantasy and whimsy. If you enjoyed the collection Imagines, you’ll love Once Upon Now!Truth Be Told by Danielle Banas Of Sirens and Beasts by Mikaela BenderWhy Yes, Bluebeard, I'd Love to by J. M. ButlerMy Love God Went to Hawaii and All I Got Was This Lousy Papaya by Debra GoelzHooded by Shannon KlareBetween Earth and Sky by R. S. KovachSleeping Beauty Syndrome by Ali NovakThe Friend Zone Promposal by Tammy OjaHome-School Hair by Christine OwenAwake by Jesse Sprague",
  "genres": [
    "Short Stories",
    "Fairy Tales",
    "Fantasy",
    "Young Adult",
    "Fairy Tale Retellings",
    "Fiction",
    "Anthologies"
  ],
  "author": "Danielle Banas",
  "average_rating": "3.46",
  "url": "https://www.goodreads.com/book/show/29868586-once-upon-now"
}