{
  "title": "Kerygma & Martyria: Puisi-Puisi Remy Sylado",
  "description": "Kerygma.\n The word, as substantive, denotes both the act and the message, and ranges in meaning from 'address' and 'call out' to 'summons' - Encyclopedia of Theology  Karl Rahner\nMartyria.\n Evidence given judicially or genitive record, repot, testimony, witness. - Dictionary of the Greek Testament Exhaustive Concordance James Strong",
  "genres": [
    "Poetry",
    "Literature",
    "Indonesian Literature"
  ],
  "author": "Remy Sylado",
  "average_rating": "3.95",
  "url": "https://www.goodreads.com/book/show/3104297-kerygma-martyria"
}