{
  "title": "Смерть и приключения Ефросиньи Прекрасной",
  "description": "В сентябре 2007 вышла книга Ольги Арефьевой \"Смерть и приключения Ефросиньи Прекрасной\". Мистический реализм, фантасмагория, парадокс, приключения, эротика. Иллюстрации Яны Клинк, иллюстратора студии Лебедева.Книга Ольги Арефьевой \"Смерть и приключения Ефросиньи Прекрасной\" получила литературную премию \"Астрея\". Премия \"Астрея\" учреждена в 2008г. как профессиональная литературная премия, присуждаемая ежегодно лучшим произведениям русскоязычной фантастики.Книгу сопровождает саунд-трек. Это диск странной электронно-шумовой музыки и сомнамбулического бреда. Пластинка называется так же, как и книга, и содержит записи голоса Ольги Арефьевой, произносящего на фоне музыкальной подложки мистические импровизации в состоянии полусна. Многие фразы вошли в книгу. Голос, текст - Ольга Арефьева Музыка - Алексей Ларионов",
  "genres": [
    "Russia"
  ],
  "author": "Ольга Арефьева",
  "average_rating": "3.63",
  "url": "https://www.goodreads.com/book/show/3595945"
}