{
  "title": "Blackburn",
  "description": "She’s my employee.I’m her boss’s boss. Hell, I own the company.Pursuing Lillian Burkette was a line I shouldn’t cross.Until a work trip from hell changed everything.I didn’t just step over the line. I annihilated the damn thing. When it comes to her, there’s nothing I wouldn’t do. I’d even kill for her.When they say the corporate world is a jungle … they have no idea.Warning - Not appropriate for readers under the age of 18.",
  "genres": [
    "Romance",
    "Contemporary Romance",
    "Novella",
    "Contemporary",
    "Romantic Suspense",
    "Military Fiction",
    "Suspense"
  ],
  "author": "Brynne Asher",
  "average_rating": "4.05",
  "url": "https://www.goodreads.com/book/show/40216554-blackburn"
}