{
  "title": "Uma noiva para Winterborne",
  "description": "Rhys Winterborne conquistou uma fortuna incalculável graças a sua ambição ferrenha. Filho de comerciante, ele se acostumou a conseguir exatamente o que quer – nos negócios e em tudo o mais.No momento em que conhece a tímida aristocrata lady Helen Ravenel, decide que ela será sua. Se for preciso macular a honra dela para garantir que se case com ele, melhor ainda.Apesar da inocência de Helen, a sedução perseverante de Rhys desperta nela uma intensa e recíproca paixão.Só que Rhys tem muitos inimigos que conspiram contra os dois. Além disso, Helen guarda um segredo sombrio que poderá separá-los para sempre. Os riscos ao amor deles são inimagináveis, mas a recompensa é uma vida inteira de felicidade.Com uma trama recheada de diálogos bem-humorados e cenas sensuais e românticas, Uma noiva para Winterborne é o segundo volume da coleção Os Ravenels.",
  "genres": [
    "Historical Romance",
    "Romance",
    "Historical",
    "Historical Fiction",
    "Audiobook",
    "Fiction",
    "Adult"
  ],
  "author": "Lisa Kleypas",
  "average_rating": "4.12",
  "url": "https://www.goodreads.com/book/show/40650760-uma-noiva-para-winterborne"
}