{
  "title": "Dramacon, Vol. 1",
  "description": "When Christie settles in the Artist Alley of her first ever anime convention, she only sees it as an opportunity to promote the comic she has started with her boyfriend. But conventions are never what you expect and soon the whirlwind of events sweeps Christie off her feet and changes her life. Who is the mysterious cosplayer that won't even take off his sunglasses indoors? What do you do when you fall in love with a guy who is going to be miles away from you in just a couple of days?",
  "genres": [
    "Manga",
    "Graphic Novels",
    "Romance",
    "Comics",
    "Young Adult",
    "Humor",
    "Comics Manga"
  ],
  "author": "Svetlana Chmakova",
  "average_rating": "4.15",
  "url": "https://www.goodreads.com/book/show/553678.Dramacon_Vol_1"
}