{
  "title": "Endless Winter",
  "description": "A brutal new Ice Age covers the Earth…When an experiment to reverse climate change goes disastrously wrong, Jarred and his daughter Hope are forced to head south in search of warmth. This man-made eternal winter shows no signs of stopping, and with temperatures continuing to plummet, fears of a new ice age drive survivors into a panic.Jarred and Hope don’t have the wilderness skills needed to survive this disaster. But when their car spins out of control, they’re forced to fend for themselves in the ruthless and unforgiving forest surrounding them. And as they journey through the snow-swept wilderness, they slowly discover they are not alone…Survivalist Fiona knows how to deal with a harsh winter on her own, but this new world is deadly. She’s got a cabin stockpiled, and is all alone until she runs across Benjy, a forest ranger who’s ready to help, but has his own reasons for staying with her.Civilization is crumbling. There’s no electricity. The cold is getting worse, and resources are scarce. To survive, Jarred and Hope will have to find allies they can trust, and push themselves harder than they ever imagined. Because even a moment’s weakness in this harsh icy wasteland can mean only one thing.Freezing to death in the merciless cold…",
  "genres": [
    "Dystopia",
    "Post Apocalyptic",
    "Apocalyptic",
    "Fiction",
    "Science Fiction"
  ],
  "author": "Riley   Miller",
  "average_rating": "4.34",
  "url": "https://www.goodreads.com/book/show/59144853-endless-winter"
}