{
  "title": "Demons of Good and Evil",
  "description": "Rachel Morgan will learn that the price of loyalty is blood...Rachel Morgan, witch-born demon, suspected that protecting the paranormal citizens of Cincinnati as the demon subrosa would be trouble. But it’s rapidly becoming way more trouble than even she could have imagined.While Rachel and her friends may have vanquished the trickster demon Hodin, his mysterious associate known only as “The Mage” is eager to finish what Hodin started, beginning with taking down Rachel’s power structure piece by piece.When he frames Rachel for the death of a powerful coven member and the vampire leaders in DC threaten to send a new master vampire to take the city in hand, Rachel’s friends Ivy and Pike are forced into hiding, and even her lover, Trent, finds himself under fire. With her world falling apart, Rachel desperately needs help. But with all of her supporters under attack, her only hope is to make a deal with the unlikeliest of allies...",
  "genres": [
    "Urban Fantasy",
    "Fantasy",
    "Paranormal",
    "Vampires",
    "Magic",
    "Witches",
    "Demons"
  ],
  "author": "Kim Harrison",
  "average_rating": "4.45",
  "url": "https://www.goodreads.com/book/show/62610073-demons-of-good-and-evil"
}