{
  "title": "Verhalen uit duizend en een nacht; Deel 14 van 16",
  "description": "Niet alleen literair behoren de Verhalen Van Duizend-en-één Nacht tot het belangrijkste wat de wereldgeschiedenis heeft opgeleverd, ze zijn ook van betekenis geweest voor historici, geologen en andere wetenschapslieden. Zo bevatten de zeven reisavonturen van Sindbad de zeeman precieze geografische inlichtingen die na wetenschappelijk onderzoek bleken te kloppen. In de plaatsnamen die voorkomen in Sindbads reisrelazen heeft men allusies gevonden op de grote etappepunten langs de zeeweg van de Perzische Golf naar het Maleise schiereiland: Java, Nicobar, Ceylon, Sumatra, Borneo. Ook voor enkele van de wonderbaarlijke avonturen die Sindbad zou hebben beleefd, blijken historische bronnen te bestaan die de authenticiteit ervan bevestigen. Over de Verhalen Van Duizend-en-één Nacht is dan ook een bibliotheek vol wetenschap en wijsheid in al ‘s Heren talen verschenen, die nog in geen mensenleven meer volledig kan worden doorgenomen.Lees de verhalen zèlf. De wetenschap en wijsheid die u er in ieder geval uit opdoet is die van het leven zelf.Dit is het veertiende deel: het boek van de achthonderdeenenzestigste tot de negenhonderdenvierde nacht.",
  "genres": [],
  "author": "Anonymous",
  "average_rating": "0.00",
  "url": "https://www.goodreads.com/book/show/13162824-verhalen-uit-duizend-en-een-nacht-deel-14-van-16"
}