{
  "title": "The Bruce Trilogy: The Steps to the Empty Throne / The Path of the Hero King / The Price of the King's Peace",
  "description": "Hero or traitor? King or outlaw? Discover the life of Scottish hero Robert the Bruce in this thrilling trilogy.Master storyteller Nigel Tranter tells the tale of the legendary warrior, and future King of Scots. Tutored and encouraged by William Wallace, Robert the Bruce determined to continue the fight for an independent Scotland, sustained by a passionate love for his land.This edition collects together Steps to the Empty Throne , Price of the King's Peace and Path of the Hero King , from the master of Scottish historical fiction.Praise for Nigel 'One of Scotland's most prolific and respected writers' Times'Through his imaginative dialogue, he provides a voice for Scotland's heroes' Scotland on Sunday",
  "genres": [
    "Historical Fiction",
    "Scotland",
    "Fiction",
    "Historical",
    "14th Century",
    "Medieval",
    "13th Century"
  ],
  "author": "Nigel Tranter",
  "average_rating": "4.34",
  "url": "https://www.goodreads.com/book/show/1460064.The_Bruce_Trilogy"
}