{
  "title": "Fix the National: And Other Racing Stories",
  "description": "Fix the National contains five short stories of racing world mysteries. In the title story, Chief Superintendent Crispin wants the judges to fix the results of the Grand National, Britain's premiere annual horse race! Even if it means catching the Birmingham bank robbers, can the Jockey Club sanction such a move?",
  "genres": [],
  "author": "Dick Francis",
  "average_rating": "0.00",
  "url": "https://www.goodreads.com/book/show/14909850-fix-the-national"
}