{
  "title": "Trouble",
  "description": "Alex Hayes doesn’t get involved. He’s been hurt before and has no desire to repeat the experience. Besides, his friends are his family. He doesn’t need anything else. Or so he thinks until he comes face-to-face with Leslie “Maestro” Hannigan… again.Two years ago, Alex was the one that got away. But now Leslie knows his name and he isn’t going to lose him twice—especially when it’s plain to see that Alex is interested in Leslie too. Alex may think Leslie is trouble… but he’s the very best kind.",
  "genres": [
    "M M Romance",
    "Contemporary",
    "Romance",
    "LGBT",
    "M M Contemporary",
    "Gay"
  ],
  "author": "Talia Carmichael",
  "average_rating": "3.97",
  "url": "https://www.goodreads.com/book/show/15853470-trouble"
}