{
  "title": "Four Summers",
  "description": "Charlotte Gates is tired of being Charlie Rae. She loves the lake she was raised on, their rental cabins, and spending her nights under the stars…but inside she yearns for more.After his freshman year, Nathaniel Chase’s family spends their first summer at The Village. From the beginning Charlotte intrigues him. She’s the girl who always says what’s on her mind, wins at night games, and each time she looks through her telescope, gets lost in the sky.Over the course of four summers together, Charlotte and Nathaniel become best friends, share firsts, mend broken hearts, protect each other’s secrets, overcome tragedies…fall in love. And say goodbye…Charlie wants out of The Village. Nate wants her to have her stars. And they dream of being able to do it all together. But life isn’t as easy as their summers.Each summer is told in alternating points of view between Charlie and Nate. Journey with the pair, and their friends, as they share their story about growing up, discovering who they are, making tough choices, and falling in love again and again.",
  "genres": [
    "Young Adult",
    "Romance",
    "Contemporary",
    "Contemporary Romance",
    "High School",
    "Young Adult Contemporary",
    "New Adult"
  ],
  "author": "Nyrae Dawn",
  "average_rating": "4.00",
  "url": "https://www.goodreads.com/book/show/17666999-four-summers"
}