{
  "title": "Shattered Blue",
  "description": "Shane MacKinnon used to be somebody else. Hounded by scandal and haunted by a shameful secret, wealthy, privileged Shannon Malone fled Manhattan and took on a new identity. Five years later, she’s finally met a man who loves her in spite of her troubled past. He’s leading her into a world of sensual pleasure she never imagined. Now a menacing whisper on the phone threatens to shatter her new life. Someone thinks she has the missing millions from a massive investment scam. Someone who also has a far more sinister reason to come after her. Shane thought the monster who tormented her childhood was dead. She was wrong. And now that he’s found her again, he’ll stop at nothing to finish his sadistic game.",
  "genres": [
    "Romance",
    "Romantic Suspense",
    "Mystery Thriller",
    "Suspense"
  ],
  "author": "Jane Taylor Starwood",
  "average_rating": "3.97",
  "url": "https://www.goodreads.com/book/show/17926886-shattered-blue"
}